{
	"info": {
		"_postman_id": "d09b4eac-86e5-4060-b33c-1c40de363a5b",
		"name": "LinKodkod server API",
		"description": "API collection for LinKodkod Server",
		"schema": "https://schema.getpostman.com/json/collection/v2.1.0/collection.json",
		"_exporter_id": "14063061"
	},
	"item": [
		{
			"name": "System",
			"item": [
				{
					"name": "API Info",
					"request": {
						"method": "GET",
						"header": [],
						"url": {
							"raw": "{{baseUrl}}/",
							"host": [
								"{{baseUrl}}"
							],
							"path": [
								""
							]
						},
						"description": "Get API information and available endpoints"
					},
					"response": []
				}
			]
		},
		{
			"name": "Posts",
			"item": [
				{
					"name": "Get All Posts",
					"request": {
						"method": "GET",
						"header": [],
						"url": {
							"raw": "{{baseUrl}}/posts",
							"host": [
								"{{baseUrl}}"
							],
							"path": [
								"posts"
							]
						},
						"description": "Get all posts"
					},
					"response": []
				},
				{
					"name": "Get Post by ID",
					"request": {
						"method": "GET",
						"header": [],
						"url": {
							"raw": "{{baseUrl}}/posts/1",
							"host": [
								"{{baseUrl}}"
							],
							"path": [
								"posts",
								"1"
							]
						},
						"description": "Get a specific post by id"
					},
					"response": []
				},
				{
					"name": "Create Post",
					"request": {
						"method": "POST",
						"header": [
							{
								"key": "Content-Type",
								"value": "application/json"
							}
						],
						"body": {
							"mode": "raw",
							"raw": "{\n    \"imgSrc\": \"/vite.svg\",\n    \"description\": \"descriptiondescription\",\n    \"likes\": 8,\n    \"author\": \"vite\",\n    \"createdAt\": \"2024-09-08T06:21:00.000Z\"\n}"
						},
						"url": {
							"raw": "{{baseUrl}}/posts",
							"host": [
								"{{baseUrl}}"
							],
							"path": [
								"posts"
							]
						},
						"description": "Create a new post"
					},
					"response": []
				},
				{
					"name": "Update Post",
					"request": {
						"method": "PUT",
						"header": [
							{
								"key": "Content-Type",
								"value": "application/json"
							}
						],
						"body": {
							"mode": "raw",
							"raw": "{\n    \"imgSrc\": \"/linkodkod.jpg\"\n}"
						},
						"url": {
							"raw": "{{baseUrl}}/posts/1",
							"host": [
								"{{baseUrl}}"
							],
							"path": [
								"posts",
								"1"
							]
						},
						"description": "Update an existing post by ID"
					},
					"response": []
				},
				{
					"name": "Delete Post",
					"request": {
						"method": "DELETE",
						"header": [],
						"url": {
							"raw": "{{baseUrl}}/posts/1",
							"host": [
								"{{baseUrl}}"
							],
							"path": [
								"posts",
								"1"
							]
						},
						"description": "Delete a post by ID"
					},
					"response": []
				}
			]
		}
	],
	"event": [
		{
			"listen": "prerequest",
			"script": {
				"type": "text/javascript",
				"packages": {},
				"exec": [
					""
				]
			}
		},
		{
			"listen": "test",
			"script": {
				"type": "text/javascript",
				"packages": {},
				"exec": [
					""
				]
			}
		}
	],
	"variable": [
		{
			"key": "baseUrl",
			"value": "http://localhost:3000",
			"description": "Base URL for the Postss Server API"
		}
	]
}